Ordfiles/arrange.py
Ordfiles-1.0.2.dist-info/LICENSE
Ordfiles-1.0.2.dist-info/METADATA
Ordfiles-1.0.2.dist-info/WHEEL
Ordfiles-1.0.2.dist-info/entry_points.txt
Ordfiles-1.0.2.dist-info/top_level.txt
Ordfiles-1.0.2.dist-info/RECORD
