Metadata-Version: 2.1
Name: Ordfiles
Version: 1.0.2
Summary: Organize your files in different folders within a directory
Home-page: https://github.com/prakhar33
Author: Prakkhar Rai
Author-email: prakhar98.rai@gmail.com
License: MIT
Platform: UNKNOWN
Classifier: License :: OSI Approved :: MIT License
Classifier: Programming Language :: Python :: 3
Classifier: Programming Language :: Python :: 3.7
Requires-Dist: setuptools
Requires-Dist: pathlib
